accepton/__init__.py
accepton/base.py
accepton/charge.py
accepton/client.py
accepton/error.py
accepton/headers.py
accepton/plan.py
accepton/promo_code.py
accepton/refund.py
accepton/request.py
accepton/response.py
accepton/subscription.py
accepton/transaction_token.py
accepton/version.py
accepton/api/__init__.py
accepton/api/planning.py
accepton/api/promotion.py
accepton/api/querying.py
accepton/api/refunding.py
accepton/api/subscribing.py
accepton/api/tokenization.py
accepton/api/utils.py
accepton-0.3.0.dist-info/DESCRIPTION.rst
accepton-0.3.0.dist-info/METADATA
accepton-0.3.0.dist-info/RECORD
accepton-0.3.0.dist-info/WHEEL
accepton-0.3.0.dist-info/metadata.json
accepton-0.3.0.dist-info/top_level.txt
